azure/ai/ml/__init__.py
azure/ai/ml/_azure_environments.py
azure/ai/ml/_exception_helper.py
azure/ai/ml/_ml_client.py
azure/ai/ml/_scope_dependent_operations.py
azure/ai/ml/_user_agent.py
azure/ai/ml/_version.py
azure/ai/ml/exceptions.py
azure/ai/ml/py.typed
azure/ai/ml/_arm_deployments/__init__.py
azure/ai/ml/_arm_deployments/arm_deployment_executor.py
azure/ai/ml/_arm_deployments/arm_helper.py
azure/ai/ml/_arm_deployments/arm_templates/__init__.py
azure/ai/ml/_arm_deployments/arm_templates/base_template.json
azure/ai/ml/_arm_deployments/arm_templates/code_version.json
azure/ai/ml/_arm_deployments/arm_templates/environment_version.json
azure/ai/ml/_arm_deployments/arm_templates/model.json
azure/ai/ml/_arm_deployments/arm_templates/model_version.json
azure/ai/ml/_arm_deployments/arm_templates/online_deployment.json
azure/ai/ml/_arm_deployments/arm_templates/online_endpoint.json
azure/ai/ml/_arm_deployments/arm_templates/update_online_endpoint.json
azure/ai/ml/_arm_deployments/arm_templates/workspace_base.json
azure/ai/ml/_arm_deployments/arm_templates/workspace_param.json
azure/ai/ml/_artifacts/__init__.py
azure/ai/ml/_artifacts/_artifact_utilities.py
azure/ai/ml/_artifacts/_blob_storage_helper.py
azure/ai/ml/_artifacts/_constants.py
azure/ai/ml/_artifacts/_fileshare_storage_helper.py
azure/ai/ml/_artifacts/_gen2_storage_helper.py
azure/ai/ml/_file_utils/__init__.py
azure/ai/ml/_file_utils/file_utils.py
azure/ai/ml/_internal/__init__.py
azure/ai/ml/_internal/_setup.py
azure/ai/ml/_internal/_schema/__init__.py
azure/ai/ml/_internal/_schema/command.py
azure/ai/ml/_internal/_schema/component.py
azure/ai/ml/_internal/_schema/environment.py
azure/ai/ml/_internal/_schema/input_output.py
azure/ai/ml/_internal/_schema/node.py
azure/ai/ml/_internal/_utils/__init__.py
azure/ai/ml/_internal/_utils/_yaml_utils.py
azure/ai/ml/_internal/dsl/__init__.py
azure/ai/ml/_internal/entities/__init__.py
azure/ai/ml/_internal/entities/_additional_includes.py
azure_ai_ml-1.8.0.dist-info/METADATA
azure_ai_ml-1.8.0.dist-info/NOTICE.txt
azure_ai_ml-1.8.0.dist-info/WHEEL
azure_ai_ml-1.8.0.dist-info/top_level.txt
azure_ai_ml-1.8.0.dist-info/RECORD
