Metadata-Version: 2.1
Name: azure-ai-ml
Version: 1.8.0
Summary: Microsoft Azure Machine Learning Client Library for Python
Home-page: https://github.com/Azure/azure-sdk-for-python
Author: Microsoft Corporation
Author-email: azuresdkengsysadmins@microsoft.com
License: MIT License
Project-URL: Bug Reports, https://github.com/Azure/azure-sdk-for-python/issues
Project-URL: Source, https://github.com/Azure/azure-sdk-python
Classifier: Development Status :: 5 - Production/Stable
Classifier: Programming Language :: Python
Classifier: Programming Language :: Python :: 3
Classifier: Programming Language :: Python :: 3 :: Only
Classifier: Programming Language :: Python :: 3.7
Classifier: Programming Language :: Python :: 3.8
Classifier: Programming Language :: Python :: 3.9
Classifier: Programming Language :: Python :: 3.10
Classifier: Programming Language :: Python :: 3.11
Classifier: License :: OSI Approved :: MIT License
Requires-Python: <4.0,>=3.7
License-File: NOTICE.txt
Requires-Dist: pyyaml (<7.0.0,>=5.1.0)
Requires-Dist: msrest (>=0.6.18)
Requires-Dist: azure-core (<2.0.0,>=1.23.0)
Requires-Dist: azure-mgmt-core (<2.0.0,>=1.3.0)
Requires-Dist: marshmallow (<4.0.0,>=3.5)
Requires-Dist: jsonschema (<5.0.0,>=4.0.0)
Requires-Dist: tqdm (<5.0.0)
Requires-Dist: strictyaml (<2.0.0)
Requires-Dist: colorama (<0.5.0)
Requires-Dist: pyjwt (<3.0.0)
Requires-Dist: azure-storage-blob (<13.0.0,>=12.10.0)
Requires-Dist: azure-storage-file-share (<13.0.0)
Requires-Dist: azure-storage-file-datalake (<13.0.0)
Requires-Dist: pydash (<6.0.0)
Requires-Dist: isodate
Requires-Dist: azure-common (<2.0.0,>=1.1)
Requires-Dist: typing-extensions (<5.0.0)
Requires-Dist: opencensus-ext-azure (<2.0.0)
Provides-Extra: designer
Requires-Dist: mldesigner ; extra == 'designer'
